README.md
setup.py
dqadk4all/__init__.py
dqadk4all/ge_lib.py
dqadk4all.egg-info/PKG-INFO
dqadk4all.egg-info/SOURCES.txt
dqadk4all.egg-info/dependency_links.txt
dqadk4all.egg-info/top_level.txt